localstack_extension_ecs_traefik_compat/__init__.py
localstack_extension_ecs_traefik_compat/extension.py
localstack_extension_ecs_traefik_compat-0.0.1.dist-info/METADATA
localstack_extension_ecs_traefik_compat-0.0.1.dist-info/WHEEL
localstack_extension_ecs_traefik_compat-0.0.1.dist-info/entry_points.txt
localstack_extension_ecs_traefik_compat-0.0.1.dist-info/licenses/LICENSE.txt
localstack_extension_ecs_traefik_compat-0.0.1.dist-info/RECORD
