Metadata-Version: 2.3
Name: localstack-extension-ecs-traefik-compat
Version: 0.0.1
Summary: LocalStack Extension: localstack-extension-ecs-traefik-compat
Project-URL: Homepage, https://github.com/the-wondersmith/localstack-extension-ecs-traefik-compat
Author-email: "Mark S." <the@wondersmith.io>
License: AGPL-3.0-or-later
Keywords: extension,localstack,localstack-extension
Requires-Python: >=3.11
